meetnotes_questions/__init__.py
meetnotes_questions/__main__.py
meetnotes_questions/meetnotes_questions.py
meetnotes_questions-0.1.12.dist-info/LICENSE.txt
meetnotes_questions-0.1.12.dist-info/METADATA
meetnotes_questions-0.1.12.dist-info/WHEEL
meetnotes_questions-0.1.12.dist-info/entry_points.txt
meetnotes_questions-0.1.12.dist-info/top_level.txt
meetnotes_questions-0.1.12.dist-info/RECORD
